{"id":"../src/components/Player/Player.scss","dependencies":[{"name":"/home/poncho/Documents/PROJET/moonboard/client/package.json","includedInParent":true,"mtime":1537734675828},{"name":"_css_loader","parent":"/home/poncho/Documents/PROJET/moonboard/client/src/components/Player/Player.scss","resolved":"/home/poncho/Documents/PROJET/moonboard/client/node_modules/parcel-bundler/src/builtins/css-loader.js"},{"name":"/home/poncho/Documents/PROJET/moonboard/client/.babelrc","includedInParent":true,"mtime":1534349358508}],"generated":{"css":".Player {\n  width: 70%;\n  height: 20rem;\n  background-position: center;\n  background-size: cover;\n  display: flex;\n  flex-direction: column;\n  justify-content: flex-end; }\n  .Player__Button {\n    display: flex;\n    justify-content: space-between;\n    align-items: center;\n    margin-bottom: 0.5rem; }\n    .Player__Button__Play {\n      width: 3rem;\n      margin: 0 0.6rem;\n      box-shadow: none;\n      text-decoration: none;\n      background-color: transparent;\n      border: none;\n      cursor: pointer; }\n    .Player__Button__Gauge {\n      width: 100%;\n      display: flex;\n      align-items: center; }\n      .Player__Button__Gauge__Volume {\n        display: flex;\n        width: 20%; }\n        .Player__Button__Gauge__Volume button {\n          width: 1.2rem;\n          box-shadow: none;\n          text-decoration: none;\n          background-color: transparent;\n          border: none;\n          padding: 0;\n          margin: 0;\n          cursor: pointer; }\n        .Player__Button__Gauge__Volume div {\n          width: 80%;\n          display: flex;\n          align-items: center; }\n          .Player__Button__Gauge__Volume div input {\n            cursor: pointer; }\n      .Player__Button__Gauge__Progress {\n        width: 80%;\n        height: 0.4rem;\n        margin-right: 0.5rem;\n        background-color: rgba(0, 0, 0, 0.4);\n        cursor: pointer; }\n        .Player__Button__Gauge__Progress .sb-soundplayer-progress-inner {\n          background-color: white;\n          height: 0.4rem;\n          border-radius: 1rem; }\n","js":"\nvar reloadCSS = require('_css_loader');\nmodule.hot.dispose(reloadCSS);\nmodule.hot.accept(reloadCSS);"},"hash":"344b5d2bfd0850b1ad34fb5f360ee192","cacheData":{"env":{}}}